LICENSE.txt
MANIFEST.in
README.md
setup.cfg
setup.py
test.py
blueapps/__init__.py
blueapps/metrics.py
blueapps/settings.py
blueapps.egg-info/PKG-INFO
blueapps.egg-info/SOURCES.txt
blueapps.egg-info/dependency_links.txt
blueapps.egg-info/entry_points.txt
blueapps.egg-info/not-zip-safe
blueapps.egg-info/requires.txt
blueapps.egg-info/top_level.txt
blueapps/account/__init__.py
blueapps/account/admin.py
blueapps/account/apps.py
blueapps/account/backends.py
blueapps/account/conf.py
blueapps/account/decorators.py
blueapps/account/forms.py
blueapps/account/middlewares.py
blueapps/account/models.py
blueapps/account/readme.md
blueapps/account/signals.py
blueapps/account/urls.py
blueapps/account/views.py
blueapps/account/components/__init__.py
blueapps/account/components/bk_jwt/__init__.py
blueapps/account/components/bk_jwt/backends.py
blueapps/account/components/bk_jwt/middlewares.py
blueapps/account/components/bk_ticket/__init__.py
blueapps/account/components/bk_ticket/backends.py
blueapps/account/components/bk_ticket/forms.py
blueapps/account/components/bk_ticket/middlewares.py
blueapps/account/components/bk_ticket/models.py
blueapps/account/components/bk_token/__init__.py
blueapps/account/components/bk_token/backends.py
blueapps/account/components/bk_token/forms.py
blueapps/account/components/bk_token/middlewares.py
blueapps/account/components/bk_token/models.py
blueapps/account/components/null/__init__.py
blueapps/account/components/ptlogin/__init__.py
blueapps/account/components/ptlogin/backends.py
blueapps/account/components/ptlogin/forms.py
blueapps/account/components/ptlogin/middlewares.py
blueapps/account/components/ptlogin/models.py
blueapps/account/components/rio/__init__.py
blueapps/account/components/rio/backends.py
blueapps/account/components/rio/forms.py
blueapps/account/components/rio/middlewares.py
blueapps/account/components/weixin/__init__.py
blueapps/account/components/weixin/backends.py
blueapps/account/components/weixin/forms.py
blueapps/account/components/weixin/middlewares.py
blueapps/account/handlers/__init__.py
blueapps/account/handlers/response.py
blueapps/account/management/__init__.py
blueapps/account/management/commands/__init__.py
