Metadata-Version: 2.1
Name: blueapps
Version: 4.15.8
Summary: development framework for blueking
Home-page: https://github.com/TencentBlueKing/blueapps
Author: blueking
Author-email: blueking@tencent.com
License: UNKNOWN
Platform: UNKNOWN
Provides-Extra: apigw-manager
Provides-Extra: bkcrypto
Provides-Extra: opentelemetry
Provides-Extra: bk-notice
